{
  "users": [
    {
      "id": 1,
      "name": "鄭丞恩",
      "email": "dandy",
      "password": "123"
    },
    {
      "id": 2,
      "name": "林庭郁",
      "email": "wendy",
      "password": "123"
    }
  ],
  "songs": [
    {
      "id": 1,
      "name": "BangBangBang",
      "artistId": 1,
      "albumId": 1,
      "like": 42,
      "audioPath": "assets/audio/audio-1.mp3"
    },
    {
      "id": 2,
      "name": "Let's Not Fall in Love",
      "artistId": 1,
      "albumId": 1,
      "like": 42,
      "audioPath": "assets/audio/audio-2.mp3"
    },
    {
      "id": 3,
      "name": "Loser",
      "artistId": 1,
      "albumId": 1,
      "like": 42,
      "audioPath": "assets/audio/audio-3.mp3"
    },
    {
      "id": 4,
      "name": "Last Dance",
      "artistId": 1,
      "albumId": 1,
      "like": 42,
      "audioPath": "assets/audio/audio-4.mp3"
    },
    {
      "id": 5,
      "name": "Fantastic Baby",
      "artistId": 1,
      "albumId": 1,
      "like": 42,
      "audioPath": "assets/audio/audio-5.mp3"
    },
    {
      "id": 6,
      "name": "Way 4 Luv",
      "artistId": 2,
      "albumId": 2,
      "like": 42,
      "audioPath": "assets/audio/audio-6.mp3"
    },
    {
      "id": 7,
      "name": "Barricades",
      "artistId": 3,
      "albumId": 3,
      "like": 42,
      "audioPath": "assets/audio/Barricades.mp3"
    },
    {
      "id": 8,
      "name": "Bauklötze",
      "artistId": 3,
      "albumId": 3,
      "like": 42,
      "audioPath": "assets/audio/Bauklötze.mp3"
    },
    {
      "id": 9,
      "name": "Call of Silence",
      "artistId": 3,
      "albumId": 3,
      "like": 42,
      "audioPath": "assets/audio/Call_of_Silence.mp3"
    },
    {
      "id": 10,
      "name": "Call your name",
      "artistId": 3,
      "albumId": 3,
      "like": 42,
      "audioPath": "assets/audio/Call_your_name.mp3"
    },
    {
      "id": 11,
      "name": "SymphonicSuite",
      "artistId": 3,
      "albumId": 3,
      "like": 42,
      "audioPath": "assets/audio/SymphonicSuite.mp3"
    },
    {
      "id": 12,
      "name": "T-KT",
      "artistId": 3,
      "albumId": 3,
      "like": 42,
      "audioPath": "assets/audio/T-KT.mp3"
    },
    {
      "id": 13,
      "name": "YouSeeBIGGIRL_TT",
      "artistId": 3,
      "albumId": 3,
      "like": 42,
      "audioPath": "assets/audio/YouSeeBIGGIRL_TT.mp3"
    },
    {
      "id": 14,
      "name": "Zero Eclipse",
      "artistId": 3,
      "albumId": 3,
      "like": 42,
      "audioPath": "assets/audio/Zero_Eclipse.mp3"
    },
    {
      "id": 15,
      "name": "시대를 초월한 마음",
      "artistId": 4,
      "albumId": 4,
      "like": 42,
      "audioPath": "assets/audio/시대를_초월한_마음.mp3"
    },
    {
      "name": "Catch Catch",
      "artistId": 5,
      "albumId": 5,
      "like": 0,
      "audioPath": "http://localhost:3000/assets/audio/catch-catch.mp3",
      "imgPath": "http://localhost:3000/mock/upload/Yena-YH-Enter-768x768.jpg",
      "id": 16
    }
  ],
  "albums": [
    {
      "id": 1,
      "imgPath": "./mock/album/album-1.webp",
      "name": "Made",
      "type": "album",
      "artistId": 1,
      "like": 52
    },
    {
      "id": 2,
      "imgPath": "./mock/album/album-2.jpg",
      "name": "ASTERUM : 134-1",
      "type": "album",
      "artistId": 2,
      "like": 52
    },
    {
      "id": 3,
      "imgPath": "./mock/album/album-3.jpg",
      "name": "澤野弘之的播放清單",
      "type": "album",
      "artistId": 3,
      "like": 52
    },
    {
      "id": 4,
      "imgPath": "./mock/album/album-4.jpg",
      "name": "鄭丞恩的播放清單",
      "type": "album",
      "artistId": 1,
      "like": 52
    },
    {
      "name": "LOVE CATCHER",
      "type": "album",
      "artistId": 5,
      "imgPath": "http://localhost:3000/mock/upload/Yena-YH-Enter-768x768.jpg",
      "like": 0,
      "id": 5
    }
  ],
  "artists": [
    {
      "id": 1,
      "imgPath": "./mock/artist/artist-1.webp",
      "name": "BigBang",
      "description": "BIGBANG（韓語：빅뱅；日語：ビッグバン）是韓國YG娛樂於2006年推出的男子團體，最初由太陽、G-Dragon、大聲[2]、T.O.P以及勝利五位成員組成，G-Dragon擔任隊長一職。團體以「宇宙大爆炸」為名，意味著將對於韓國音樂界，甚至在全世界帶來爆炸性的影響。官方的歌迷名稱則是「V.I.P」，其意思為「Very Important Person」，是根據第二張單曲《BIGBANG Is V.I.P》命名，有著粉絲是非常重要的人的含義。"
    },
    {
      "id": 2,
      "imgPath": "./mock/artist/artist-2.jpg",
      "name": "PLAVE",
      "description": "PLAVE（韓語：플레이브；日語：プレイブ）是韓國VLAST於2023年推出的虛擬男子團體，由五位成員組成，分別為諾亞、藝俊、斑比、銀虎與河玟，並由藝俊擔任隊長。"
    },
    {
      "id": 3,
      "imgPath": "./mock/artist/artist-3.jpg",
      "name": "澤野弘之",
      "description": "澤野弘之，日本作曲家、編曲家，出生於東京都。代表配樂作品有電視劇《醫龍》系列、動畫《機動戰士鋼彈UC》、《罪惡王冠》、《進擊的巨人》、《KILL la KILL》、《青之驅魔師》、《終結的熾天使》、《七大罪》等。"
    },
    {
      "id": 4,
      "imgPath": "./mock/artist/DIAN.jpg",
      "name": "DIAN",
      "description": "以獨特聲線與細膩情感受到關注的韓國創作者型歌手。DIAN 擅長將日常情緒與青春感融入音樂之中，結合柔和旋律、輕電子與 K-Indie 氛圍，打造帶有深夜感性的作品風格。除了音樂創作外，也透過 YouTube 分享生活與創作日常，以真實自然的魅力累積全球粉絲喜愛。"
    },
    {
      "name": "崔叡娜",
      "imgPath": "./mock/unnamed.png",
      "description": "",
      "id": 5
    }
  ],
  "playlists": [
    {
      "id": 1,
      "name": "Dandy的最愛",
      "userId": 1,
      "type": "playlist"
    },
    {
      "id": 2,
      "name": "Wendy的最愛",
      "userId": 2,
      "type": "playlist"
    },
    {
      "id": 3,
      "name": "Dandy和Wendy的最愛",
      "userId": 1,
      "type": "playlist"
    },
    {
      "name": "我喜歡的歌曲",
      "userId": 1,
      "type": "favorite",
      "id": 5
    },
    {
      "name": "垃圾幫",
      "userId": 1,
      "type": "playlist",
      "id": 8
    }
  ],
  "playlistUsers": [
    {
      "id": 1,
      "playlistId": 1,
      "userId": 1
    },
    {
      "id": 2,
      "playlistId": 2,
      "userId": 2
    },
    {
      "id": 3,
      "playlistId": 3,
      "userId": 1
    },
    {
      "id": 4,
      "playlistId": 3,
      "userId": 2
    },
    {
      "playlistId": 5,
      "userId": 1,
      "id": 6
    },
    {
      "playlistId": 8,
      "userId": 1,
      "id": 9
    }
  ],
  "playlistSongs": [
    {
      "id": 3,
      "playlistId": 3,
      "songId": 3
    },
    {
      "playlistId": 3,
      "songId": 8,
      "id": 7
    },
    {
      "playlistId": 3,
      "songId": 15,
      "id": 9
    },
    {
      "playlistId": 3,
      "songId": 3,
      "id": 10
    },
    {
      "playlistId": 3,
      "songId": 3,
      "id": 11
    },
    {
      "playlistId": 3,
      "songId": 15,
      "id": 12
    },
    {
      "playlistId": 1,
      "songId": 3,
      "id": 13
    },
    {
      "playlistId": 5,
      "songId": 5,
      "id": 15
    },
    {
      "playlistId": 5,
      "songId": 7,
      "id": 16
    },
    {
      "playlistId": 5,
      "songId": 8,
      "id": 17
    },
    {
      "playlistId": 5,
      "songId": 9,
      "id": 18
    },
    {
      "playlistId": 5,
      "songId": 10,
      "id": 19
    },
    {
      "playlistId": 5,
      "songId": 1,
      "id": 20
    },
    {
      "playlistId": 5,
      "songId": 2,
      "id": 21
    },
    {
      "playlistId": 5,
      "songId": 15,
      "id": 22
    },
    {
      "playlistId": 5,
      "songId": 3,
      "id": 23
    }
  ]
}